CHANGELOG.txt
LICENCE.txt
MANIFEST.in
README.txt
__init__.py
setup.py
Cars/Audi.py
Cars/BMW.py
Cars/__init__.py
Two_Wheeler/Activa.py
Two_Wheeler/Fascino.py
Two_Wheeler/__init__.py
Vehicles.egg-info/PKG-INFO
Vehicles.egg-info/SOURCES.txt
Vehicles.egg-info/dependency_links.txt
Vehicles.egg-info/top_level.txt