Metadata-Version: 1.0
Name: Vehicles
Version: 0.0.1
Summary: It is a base on Vehicles type and its module.
Home-page: https://github.com/PrachiiiShah
Author: Prachi shah
Author-email: prachivshah03@gmail.com
License: MIT
Keywords: vehicletype
Platform: UNKNOWN
